marzban/__init__.py
marzban/api.py
marzban/models.py
marzban/utils.py
marzban-0.4.3.dist-info/licenses/LICENSE
marzban-0.4.3.dist-info/METADATA
marzban-0.4.3.dist-info/WHEEL
marzban-0.4.3.dist-info/top_level.txt
marzban-0.4.3.dist-info/RECORD
