Metadata-Version: 2.4
Name: marzban
Version: 0.4.3
Summary: Асинхронная библиотека Python для взаимодействия с MarzbanAPI | Поддерживает работу через HTTPS/SSH
Home-page: https://github.com/sm1ky/marzban_api
Author: Artem
Author-email: contant@sm1ky.com
Project-URL: Homepage, https://github.com/sm1ky/marzban_api
Project-URL: Documentation [EN], https://github.com/sm1ky/marzban_api/blob/development/.readme/README_en.md
Project-URL: Documentation [RU], https://github.com/sm1ky/marzban_api/blob/development/.readme/README_ru.md
Project-URL: Source, https://github.com/sm1ky/marzban_api
Project-URL: Developer, https://t.me/sm1ky
Classifier: Programming Language :: Python :: 3
Classifier: License :: OSI Approved :: MIT License
Classifier: Operating System :: OS Independent
Requires-Python: >=3.9
License-File: LICENSE
Requires-Dist: httpx>=0.23.0
Requires-Dist: pydantic>=1.10.0
Requires-Dist: paramiko>=3.5.0
Requires-Dist: sshtunnel>=0.4.0
Requires-Dist: datetime>=5.5
Dynamic: author
Dynamic: author-email
Dynamic: classifier
Dynamic: description
Dynamic: description-content-type
Dynamic: home-page
Dynamic: license-file
Dynamic: project-url
Dynamic: requires-dist
Dynamic: requires-python
Dynamic: summary
